Workbook

Sheet Bovinos_Activos
A1: FINCA | B1: Nombre/Arete | C1: Arete | D1: Sexo | E1: Edad (texto) | F1: Peso (texto) | G1: Peso (kg) | H1: Raza | I1: Fecha Nacimiento | J1: Anotaciones | K1: Edad (años aprox)
A2: Guadalupe | B2: Victoria | C2: 6 | D2: Hembra | E2: 7 Años | F2: 500kgs | G2: 500 | H2: F1 Simbrah | I2: Desconocida
A3: Guadalupe | B3: Paturra | C3: 10 | D3: Hembra | E3: 4 Años | F3: 300kg | G3: 300 | H3: Brahman PATURRA | I3: Desconocida
A4: Guadalupe | B4: Reina de Cartagena | C4: 16 | D4: Hembra | E4: 7 años | F4: 400kgs | G4: 400 | H4: GYR | I4: 43313 | J4: Tiene Registro Asocebu
A5: Guadalupe | B5: 403-Indira | C5: 403 | D5: Hembra | E5: 3 años | F5: 400kgs | G5: 400 | H5: Girolanda F1
A6: Guadalupe | B6: Hijo de Indira H de 403 | C6: 11 | D6: Macho | E6: 4 meses | F6: 40kgs | G6: 40 | H6: Girolanda F2 | I6: 45915
A7: Guadalupe | B7: 21 | C7: 21 | D7: Hembra | E7: 2 años | F7: 400kgs | G7: 400 | H7: Girolanda F1 | J7: Enferma en emergencia invernal
A8: Guadalupe | B8: Hijo de 021 "Tomas de Aquino" | D8: Macho | E8: RN | H8: Girolanda F2 | I8: 46051 | J8: Ternero enfermo a los 15 dias de nacido
A9: Guadalupe | B9: 47 "mamá de Copito" | C9: 47 | D9: Hembra | E9: 3 Años | F9: 400kgs | G9: 400 | H9: Girolanda F1 | J9: Enferma en emergencia invernal
A10: Guadalupe | B10: Hijo de 047- "Copito" | D10: Macho | E10: 3 meses | F10: 35kgs | G10: 35 | H10: Girolanda F2 | I10: 45943 | J10: Nació enfermo, tratado por 5 dias con ATB y vitaminas, recuperado ok
A11: Guadalupe | B11: H de 073 "BLAS"- Huerfano | D11: Macho | E11: 2 meses | F11: 35Kgs | G11: 35 | H11: Girolando F2 | I11: 45977 | J11: Nacio debil, temblor, recibio calsyn 1er dia, curacion de ombligo, se recuperó a las 48 horas, huerfano.
A12: Guadalupe | B12: 53 | C12: 53 | D12: Hembra | E12: 3 Años | F12: 400kgs | G12: 400 | H12: Girolanda F1
A13: Guadalupe | B13: Hijo de 053 "Lluvia" | D13: Hembra | E13: RN | H13: Girolanda F2 | I13: 46057 | J13: RN ok
A14: Guadalupe | B14: 45 "Azabache" | D14: Hembra | E14: 3 Años | F14: 400kgs | G14: 400 | H14: Girolanda F1
A15: Guadalupe | B15: Hijo de 045 "Diana" | C15: 45 | D15: Hembra | E15: RN | F15: 35Kgs | G15: 35 | H15: Girolanda F2 | I15: 46036 | J15: RN ok
A16: Guadalupe | B16: 38 | C16: 38 | D16: Hembra | E16: 3 años | F16: 400kgs | G16: 400 | H16: Girolanda F1
A17: Guadalupe | B17: 186 "Noche" | C17: 186 | D17: Hembra | E17: 3 años | F17: 400kgs | G17: 400 | H17: Girolanda F1
A18: Guadalupe | B18: Hijo de 186 "Noche" | D18: Macho | E18: 2 meses | H18: Girolanda F2 | I18: 45969 | J18: RN ok
A19: Guadalupe | B19: 52 "Nikita" | C19: 52 | D19: Hembra | E19: 3 años | F19: 400kgs | G19: 400 | H19: Girolanda F1 | J19: Hematura persistente
A20: Guadalupe | B20: Hijo de 052 "Nikita" | D20: Hembra | E20: 1 mes | H20: Girolanda F2 | I20: 45998
A21: Guadalupe | B21: 78 | C21: 78 | D21: Hembra | E21: 3 años | F21: 400kgs | G21: 400 | H21: Girolanda F1
A22: Guadalupe | B22: 1317 "Cariñosa" | C22: 1317 | D22: Hembra | E22: 3 años | F22: 400kgs | G22: 400 | H22: Girolanda F1
A23: Guadalupe | B23: Hijo de 1317 "Cariñito" | D23: Hembra | E23: RN | F23: 35Kgs | G23: 35 | H23: Girolanda F2 | I23: 46031 | J23: RN ok
A24: Guadalupe | B24: 1152 | C24: 1152 | D24: Hembra | E24: 3 años | F24: 400kgs | G24: 400 | H24: Girolanda F1
A25: Guadalupe | B25: 818-3 | C25: 818 | D25: Hembra | E25: 2 años | F25: 400kgs | G25: 400 | H25: Girolanda F1 | I25: 45174 | J25: Tiene Registro Asocebu
A26: 3C | B26: Shakira | C26: 4 | D26: Hembra | E26: 6 Años | F26: 300 | G26: 300 | H26: Parda Suizo x Cebu PATURRA | I26: Desconocida | J26: Se traslada a 3C el 22-01-27
A27: 3C | B27: Siete Mujeres | C27: 3 | D27: Macho | E27: 3 años | F27: 250kg Aprox | G27: 250 | H27: Cebu Paturro | I27: Desconocida | J27: Se traslada a 3C el 22-01-28
A28: 3C | B28: Carol | C28: 22 | D28: Hembra | E28: 4 meses | H28: No especifico | I28: 45905 | J28: Se traslada a 3C el 22-01-29
A29: 3C | B29: Paturra Hija | C29: 14 | D29: Hembra | E29: 1 año | F29: 200 | G29: 200 | H29: Brahman Rojo PATURRA | I29: Desconocida | J29: 14-09-25 Se retira dren de Abceso en buen estado general, gluteo ok. Se desconoce el origen.
A30: 3C | B30: Ramsés | C30: 1 | D30: Macho | E30: 1 año | F30: 180 | G30: 180 | H30: Red Shindi | I30: 45646 | J30: Tiene Registro Asocebu
A31: 3C | B31: 320-N23 | C31: 320 | D31: Hembra | E31: 2 años | F31: 400kgs | G31: 400 | H31: Girolanda
A32: 3C | B32: 348-124 | C32: 348 | D32: Hembra | E32: 2 años | F32: 400kgs | G32: 400 | H32: Girolanda Plus | I32: 45307 | J32: Tiene Registro Asocebu
A33: 3C | B33: 330-D23 | C33: 330 | D33: Hembra | E33: 2 años | F33: 400kgs | G33: 400 | H33: Girolanda Plus | I33: 45270 | J33: Tiene Registro Asocebu
A34: 3C | B34: 327-D23 | C34: 327 | D34: Hembra | E34: 2 años | F34: 400kgs | G34: 400 | H34: Girolanda Plus | I34: 45270 | J34: Tiene Registro Asocebu
A35: 3C | B35: 347-124 | C35: 347 | D35: Hembra | E35: 2 años | F35: 400kgs | G35: 400 | H35: Girolanda Plus | I35: 45304 | J35: Tiene Registro Asocebu
A36: 3C | B36: 328-D23 | C36: 328 | D36: Hembra | E36: 2 años | F36: 400kgs | G36: 400 | H36: Girolanda Plus | I36: 45270 | J36: Tiene Registro Asocebu
A37: 3C | B37: 350-124 | C37: 350 | D37: Hembra | E37: 2 años | F37: 400kgs | G37: 400 | H37: Girolanda Plus | I37: 45309 | J37: Tiene Registro Asocebu
A38: 3C | B38: 345-124 | C38: 345 | D38: Hembra | E38: 2 años | F38: 400kgs | G38: 400 | H38: Girolanda Plus | I38: 45304 | J38: Tiene Registro Asocebu
A39: 3C | B39: Dina Luz - 018 | C39: 18 | D39: Hembra | E39: 1 año | F39: 150kgs | G39: 150 | H39: Red Shindi | I39: 45685 | J39: Tiene Registro Asocebu
A40: 3C | B40: 1751 | C40: 1751 | D40: Hembra | E40: 5 años | F40: 580kgs | G40: 580 | H40: Simbrah | I40: 44166 | J40: Tiene Registro Asocebu
A41: 3C | B41: Hijo de 1751 | C41: 42 | D41: Hembra | E41: 5 meses | H41: Simbrah | I41: 45916
A42: 3C | B42: 1757-0 | C42: 1557 | D42: Hembra | E42: 5 años | F42: 580kgs | G42: 580 | H42: Simbrah | I42: 44166 | J42: Tiene Registro Asocebu
A43: 3C | B43: Hijo de 1757-0 | C43: 29 | D43: Macho | E43: 1 mes | H43: Simbrah | I43: 45998
A44: 3C | B44: 1731-0 | C44: 1731 | D44: Hembra | E44: 5 años | F44: 580kgs | G44: 580 | H44: Simbrah
A45: 3C | B45: Hijo de 1731-0 | C45: 31 | D45: Macho | E45: 3 meses | H45: Simbrah | I45: 45953
A46: 3C | B46: 1697-0 | C46: 1697 | D46: Hembra | E46: 5 años | F46: 580kgs | G46: 580 | H46: Simbrah
A47: 3C | B47: Hijo de 1697-0 | C47: 33 | D47: Hembra | E47: 4 meses | F47: 45kgs | G47: 45 | H47: Simbrah | I47: 45939
A48: 3C | B48: 1799-0 | C48: 1799 | D48: Hembra | E48: 5 años | F48: 580kgs | G48: 580 | H48: Simbrah | I48: 44169
A49: 3C | B49: Hijo de 1799-0 | C49: 35 | D49: Macho | E49: 2 meses | H49: Simbrah | I49: 46003
A50: 3C | B50: 504-220 | C50: 504 | D50: Hembra | E50: 6 años | F50: 600kgs | G50: 600 | H50: Simbrah | I50: 43881 | J50: Tiene Registro Asosimbrah
A51: 3C | B51: Hijo de 504-220 | C51: 44 | D51: Hembra | E51: 3 meses | H51: Simbrah | I51: 45983
A52: 3C | B52: 1479-0 | C52: 1479 | D52: Hembra | E52: 5 años | F52: 580kgs | G52: 580 | H52: Simbrah | I52: 44127
A53: 3C | B53: Hijo de 1479-0 | C53: 46 | D53: Hembra | H53: Simbrah
A54: 3C | B54: 116-9 | C54: 116-9 | D54: Hembra | E54: 6 años | F54: 580kgs | G54: 580 | H54: Simbrah | I54: 43829 | J54: Tiene Registro Asosimbrah
A55: 3C | B55: 1726 | C55: 1726 | D55: Hembra | F55: 580kgs | G55: 580 | H55: Simbrah
A56: 3C | B56: 1810-0 | C56: 1810 | D56: Hembra | E56: 5 años | F56: 580kgs | G56: 580 | H56: Simbrah | I56: 44175
A57: 3C | B57: 127 | C57: 127 | D57: Hembra | E57: 3 años | F57: 400kgs | G57: 400 | H57: Girolanda F1 | J57: 13-02-26 Se traslada de Guadalupe a 3C por emergencia invernal
A58: 3C | B58: 49 | C58: 49 | D58: Hembra | E58: 3 años | F58: 400kgs | G58: 400 | H58: Girolanda F1 | J58: 13-02-26 Se traslada de Guadalupe a 3C por emergencia invernal
A59: 3C | B59: 57 | C59: 57 | D59: Hembra | E59: 3 años | F59: 400kgs | G59: 400 | H59: Girolanda F1 | J59: 13-02-26 Se traslada de Guadalupe a 3C por emergencia invernal
A60: 3C | B60: 294-123 | C60: 294 | D60: Hembra | E60: 2 años | F60: 400kgs | G60: 400 | H60: Girolanda Plus | I60: 45125 | J60: 13-02-26 Se traslada de Guadalupe a 3C por emergencia invernal
A61: 3C | B61: 310-923 | C61: 310 | D61: Hembra | E61: 2 años | F61: 400kgs | G61: 400 | H61: Girolanda Plus | I61: 45184 | J61: 13-02-26 Se traslada de Guadalupe a 3C por emergencia invernal

Sheet Bovinos_Bruto
A1: Estado/Nota | B1: FINCA | C1: Nombre/Arete | D1: Arete | E1: Sexo | F1: Edad | G1: Peso | H1: Raza | I1: Fecha Nacimiento | J1: Anotaciones
A2: Baja, vendida- Emergencia invernal | B2: 3C | C2: Clara | D2: 2 | E2: Hembra | F2: 6 Años | G2: 300 | H2: Cebú PATURRA | I2: Desconocida | J2: Se traslada a 3C el 22-01-26
B3: 3C | C3: Shakira | D3: 4 | E3: Hembra | F3: 6 Años | G3: 300 | H3: Parda Suizo x Cebu PATURRA | I3: Desconocida | J3: Se traslada a 3C el 22-01-27
B4: 3C | C4: Siete Mujeres | D4: 3 | E4: Macho | F4: 3 años | G4: 250kg Aprox | H4: Cebu Paturro | I4: Desconocida | J4: Se traslada a 3C el 22-01-28
B5: 3C | C5: Carol | D5: 22 | E5: Hembra | F5: 4 meses | H5: No especifico | I5: 45905 | J5: Se traslada a 3C el 22-01-29
A6: Baja, vendida- Emergencia invernal | B6: 3C | C6: Roy "Punto Blanco" | D6: 5 | E6: Macho | F6: 5 meses | H6: Cebu Paturro | I6: 45886 | J6: Se traslada a 3C el 22-01-30
A7: Baja, vendida- Emergencia invernal | B7: 3C | C7: Victor de las 3 cumbres | D7: 7 | E7: Macho | F7: 9 meses | H7: F2 | I7: 45773 | J7: Se traslada a 3C el 22-01-31
A8: Baja, vendida- Emergencia invernal | B8: 3C | C8: Lucero Hijo | D8: 9 | E8: Macho | F8: 1 año | H8: No especifico | I8: Desconocida | J8: Se traslada a 3C el 22-01-32
B9: 3C | C9: Paturra Hija | D9: 14 | E9: Hembra | F9: 1 año | G9: 200 | H9: Brahman Rojo PATURRA | I9: Desconocida | J9: 14-09-25 Se retira dren de Abceso en buen estado general, gluteo ok. Se desconoce el origen.
B10: 3C | C10: Ramsés | D10: 1 | E10: Macho | F10: 1 año | G10: 180 | H10: Red Shindi | I10: 45646 | J10: Tiene Registro Asocebu
B11: 3C | C11: 320-N23 | D11: 320 | E11: Hembra | F11: 2 años | G11: 400kgs | H11: Girolanda
B12: 3C | C12: 348-124 | D12: 348 | E12: Hembra | F12: 2 años | G12: 400kgs | H12: Girolanda Plus | I12: 45307 | J12: Tiene Registro Asocebu
B13: 3C | C13: 330-D23 | D13: 330 | E13: Hembra | F13: 2 años | G13: 400kgs | H13: Girolanda Plus | I13: 45270 | J13: Tiene Registro Asocebu
B14: 3C | C14: 327-D23 | D14: 327 | E14: Hembra | F14: 2 años | G14: 400kgs | H14: Girolanda Plus | I14: 45270 | J14: Tiene Registro Asocebu
B15: 3C | C15: 347-124 | D15: 347 | E15: Hembra | F15: 2 años | G15: 400kgs | H15: Girolanda Plus | I15: 45304 | J15: Tiene Registro Asocebu
B16: 3C | C16: 328-D23 | D16: 328 | E16: Hembra | F16: 2 años | G16: 400kgs | H16: Girolanda Plus | I16: 45270 | J16: Tiene Registro Asocebu
B17: 3C | C17: 350-124 | D17: 350 | E17: Hembra | F17: 2 años | G17: 400kgs | H17: Girolanda Plus | I17: 45309 | J17: Tiene Registro Asocebu
B18: 3C | C18: 345-124 | D18: 345 | E18: Hembra | F18: 2 años | G18: 400kgs | H18: Girolanda Plus | I18: 45304 | J18: Tiene Registro Asocebu
B19: 3C | C19: Dina Luz - 018 | D19: 18 | E19: Hembra | F19: 1 año | G19: 150kgs | H19: Red Shindi | I19: 45685 | J19: Tiene Registro Asocebu
B20: 3C | C20: 1751 | D20: 1751 | E20: Hembra | F20: 5 años | G20: 580kgs | H20: Simbrah | I20: 44166 | J20: Tiene Registro Asocebu
B21: 3C | C21: Hijo de 1751 | D21: 42 | E21: Hembra | F21: 5 meses | H21: Simbrah | I21: 45916
B22: 3C | C22: 1757-0 | D22: 1557 | E22: Hembra | F22: 5 años | G22: 580kgs | H22: Simbrah | I22: 44166 | J22: Tiene Registro Asocebu
B23: 3C | C23: Hijo de 1757-0 | D23: 29 | E23: Macho | F23: 1 mes | H23: Simbrah | I23: 45998
B24: 3C | C24: 1731-0 | D24: 1731 | E24: Hembra | F24: 5 años | G24: 580kgs | H24: Simbrah
B25: 3C | C25: Hijo de 1731-0 | D25: 31 | E25: Macho | F25: 3 meses | H25: Simbrah | I25: 45953
B26: 3C | C26: 1697-0 | D26: 1697 | E26: Hembra | F26: 5 años | G26: 580kgs | H26: Simbrah
B27: 3C | C27: Hijo de 1697-0 | D27: 33 | E27: Hembra | F27: 4 meses | G27: 45kgs | H27: Simbrah | I27: 45939
B28: 3C | C28: 1799-0 | D28: 1799 | E28: Hembra | F28: 5 años | G28: 580kgs | H28: Simbrah | I28: 44169
B29: 3C | C29: Hijo de 1799-0 | D29: 35 | E29: Macho | F29: 2 meses | H29: Simbrah | I29: 46003
B30: 3C | C30: 504-220 | D30: 504 | E30: Hembra | F30: 6 años | G30: 600kgs | H30: Simbrah | I30: 43881 | J30: Tiene Registro Asosimbrah
B31: 3C | C31: Hijo de 504-220 | D31: 44 | E31: Hembra | F31: 3 meses | H31: Simbrah | I31: 45983
B32: 3C | C32: 1479-0 | D32: 1479 | E32: Hembra | F32: 5 años | G32: 580kgs | H32: Simbrah | I32: 44127
B33: 3C | C33: Hijo de 1479-0 | D33: 46 | E33: Hembra | H33: Simbrah
B34: 3C | C34: 116-9 | D34: 116-9 | E34: Hembra | F34: 6 años | G34: 580kgs | H34: Simbrah | I34: 43829 | J34: Tiene Registro Asosimbrah
B35: 3C | C35: 1726 | D35: 1726 | E35: Hembra | G35: 580kgs | H35: Simbrah
B36: 3C | C36: 1810-0 | D36: 1810 | E36: Hembra | F36: 5 años | G36: 580kgs | H36: Simbrah | I36: 44175
B37: 3C | C37: 1697-0 | D37: 1697 | E37: Hembra | F37: 5 años | G37: 580kgs | H37: Simbrah
B38: 3C | C38: Hijo de 1697 | D38: 48 | E38: Hembra | F38: 4 meses | H38: Simbrah | I38: 45939
B39: Guadalupe | C39: Victoria | D39: 6 | E39: Hembra | F39: 7 Años | G39: 500kgs | H39: F1 Simbrah | I39: Desconocida
A40: Vendida | B40: Guadalupe | C40: Lucero | D40: 8 | E40: Hembra | F40: 5 Años | G40: 400kg Aprox | H40: Girolanda F2 | I40: Desconocida
B41: Guadalupe | C41: Paturra | D41: 10 | E41: Hembra | F41: 4 Años | G41: 300kg | H41: Brahman PATURRA | I41: Desconocida
B42: Guadalupe | C42: Reina de Cartagena | D42: 16 | E42: Hembra | F42: 7 años | G42: 400kgs | H42: GYR | I42: 43313 | J42: Tiene Registro Asocebu
B43: Guadalupe | C43: 403-Indira | D43: 403 | E43: Hembra | F43: 3 años | G43: 400kgs | H43: Girolanda F1
A44: Destete en Abril | B44: Guadalupe | C44: Hijo de Indira H de 403 | D44: 11 | E44: Macho | F44: 4 meses | G44: 40kgs | H44: Girolanda F2 | I44: 45915
B45: Guadalupe | C45: 21 | D45: 21 | E45: Hembra | F45: 2 años | G45: 400kgs | H45: Girolanda F1
A46: Destete en agosto | B46: Guadalupe | C46: Hijo de 021 "Tomas de Aquino" | E46: Macho | F46: RN | H46: Girolanda F2 | I46: 46051
B47: Guadalupe | C47: 47 "mamá de Copito" | D47: 47 | E47: Hembra | F47: 3 Años | G47: 400kgs | H47: Girolanda F1
A48: Destete en Abril | B48: Guadalupe | C48: Hijo de 047- "Copito" | E48: Macho | F48: 3 meses | G48: 35kgs | H48: Girolanda F2 | I48: 45943 | J48: Nació enfermo, tratado por 5 dias con ATB y vitaminas, recuperado ok
A49: Destete en Mayo | B49: Guadalupe | C49: H de 073 "BLAS"- Huerfano | E49: Macho | F49: 2 meses | G49: 35Kgs | H49: Girolando F2 | I49: 45977 | J49: Nacio debil, temblor, recibio calsyn 1er dia, curacion de ombligo, se recuperó a las 48 horas, huerfano.
B50: Guadalupe | C50: 53 | D50: 53 | E50: Hembra | F50: 3 Años | G50: 400kgs | H50: Girolanda F1
A51: Destete en agosto | B51: Guadalupe | C51: Hijo de 053 "Lluvia" | E51: Hembra | F51: RN | H51: Girolanda F2 | I51: 46057 | J51: RN ok
B52: Guadalupe | C52: 45 "Azabache" | E52: Hembra | F52: 3 Años | G52: 400kgs | H52: Girolanda F1
A53: Destete en julio | B53: Guadalupe | C53: Hijo de 045 "Diana" | D53: 45 | E53: Hembra | F53: RN | G53: 35Kgs | H53: Girolanda F2 | I53: 46036 | J53: RN ok
B54: Guadalupe | C54: 38 | D54: 38 | E54: Hembra | F54: 3 años | G54: 400kgs | H54: Girolanda F1
B55: 3C | C55: 127 | D55: 127 | E55: Hembra | F55: 3 años | G55: 400kgs | H55: Girolanda F1 | J55: 13-02-26 Se traslada de Guadalupe a 3C por emergencia invernal
B56: Guadalupe | C56: 186 "Noche" | D56: 186 | E56: Hembra | F56: 3 años | G56: 400kgs | H56: Girolanda F1
A57: Destete en Mayo | B57: Guadalupe | C57: Hijo de 186 "Noche" | E57: Macho | F57: 2 meses | H57: Girolanda F2 | I57: 45969
B58: Guadalupe | C58: 52 "Nikita" | D58: 52 | E58: Hembra | F58: 3 años | G58: 400kgs | H58: Girolanda F1
A59: Destete en Junio | B59: Guadalupe | C59: Hijo de 052 "Nikita" | E59: Hembra | F59: 1 mes | H59: Girolanda F2 | I59: 45998
B60: Guadalupe | C60: 78 | D60: 78 | E60: Hembra | F60: 3 años | G60: 400kgs | H60: Girolanda F1
B61: 3C | C61: 49 | D61: 49 | E61: Hembra | F61: 3 años | G61: 400kgs | H61: Girolanda F1 | J61: 13-02-26 Se traslada de Guadalupe a 3C por emergencia invernal
B62: 3C | C62: 57 | D62: 57 | E62: Hembra | F62: 3 años | G62: 400kgs | H62: Girolanda F1 | J62: 13-02-26 Se traslada de Guadalupe a 3C por emergencia invernal
B63: Guadalupe | C63: 1317 "Cariñosa" | D63: 1317 | E63: Hembra | F63: 3 años | G63: 400kgs | H63: Girolanda F1
A64: Destete en julio | B64: Guadalupe | C64: Hijo de 1317 "Cariñito" | E64: Hembra | F64: RN | G64: 35Kgs | H64: Girolanda F2 | I64: 46031
B65: Guadalupe | C65: 1152 | D65: 1152 | E65: Hembra | F65: 3 años | G65: 400kgs | H65: Girolanda F1
B66: 3C | C66: 294-123 | D66: 294 | E66: Hembra | F66: 2 años | G66: 400kgs | H66: Girolanda Plus | I66: 45125 | J66: 13-02-26 Se traslada de Guadalupe a 3C por emergencia invernal
B67: 3C | C67: 310-923 | D67: 310 | E67: Hembra | F67: 2 años | G67: 400kgs | H67: Girolanda Plus | I67: 45184 | J67: 13-02-26 Se traslada de Guadalupe a 3C por emergencia invernal
B68: Guadalupe | C68: 818-3 | D68: 818 | E68: Hembra | F68: 2 años | G68: 400kgs | H68: Girolanda F1 | I68: 45174 | J68: Tiene Registro Asocebu
A69: Baja - | B69: Guadalupe/MORTINATO | C69: Hijo de 818 | E69: Hembra | F69: RN | G69: 35Kgs | H69: Girolanda F2 | I69: 01-01-26 Mortinato

Sheet Medicamentos
A1: Finca | B1: Nombre | C1: Sexo | D1: Fecha | E1: Medicamento/Procedimiento | F1: Responsable | G1: Plan | H1: Costo (COP) | I1: Notas
A2: 3C | B2: 504 | C2: Hembra | D2: 46051 | E2: Ricomax 15cc subcutáneo-Vacuna Reproductiv. Eco: útero sin tono folículo grande ovario derecho útero en anestro. | F2: Dr. Zuñiga | G2: Minerales y preñar | H2: 0
A3: 3C | B3: Hijo de 504 | C3: Hembra | D3: 46051 | E3: Ricomax 5ml-Vacuna carbon 1era dosis | F3: Dr. Zuñiga | G3: Dosis de refuerzo el 19-02-26 | H3: 0
A4: 3C | B4: 1479-0 | C4: Hembra | D4: 46051 | E4: Ricomax 15cc subcutáneo-Vacuna Reproductiv. Edoantripan 20cc c/l. Eco: útero sin tono folículo grande ovario derecho útero en anestro. | F4: Dr. Zuñiga | G4: Minerales y preñar- Dosis de refuerzo el 19-02-26 | H4: 0
A5: 3C | B5: 1751-0 | C5: Hembra | D5: 46051 | E5: Ricomax 15cc subcutáneo-Vacuna Reproductiv. Edoantripan 60cc 3/l. Eco: útero sin tono folículo grande ovario derecho útero en anestro. | F5: Dr. Zuñiga | G5: Minerales y preñar- Dosis de refuerzo el 19-02-27 | H5: 0
A6: 3C | B6: Hijo de 1751 | C6: Hembra | D6: 46051 | E6: Ricomax 5ml-Vacuna carbon 1era dosis | F6: Dr. Zuñiga | G6: Dosis de refuerzo el 19-02-26 | H6: 0
A7: 3C | B7: 1731-0 | C7: Hembra | D7: 46051 | E7: Ricomax 15cc subcutáneo-Vacuna Reproductiv. Imidocar- Eco: útero sin tono útero en anestro. Abcseso en gluteo, impresiona babesia, No ordeñar. | F7: Dr. Zuñiga | G7: Minerales y preñar- Dosis de refuerzo el 19-02-27 | H7: 0
A8: 3C | B8: Hijo de 1731 | C8: Macho | D8: 46051 | E8: Ricomax 5ml-Vacuna carbon 1era dosis | F8: Dr. Zuñiga | G8: Dosis de refuerzo el 19-02-26 | H8: 0
A9: 3C | B9: 1799 | C9: Hembra | D9: 46051 | E9: Ricomax 15cc subcutáneo-Vacuna Reproductiv. Imidocar- Eco: útero sin tono útero en anestro. Abcseso en gluteo, se drenó, impresiona babesia, No ordeñar. | F9: Dr. Zuñiga | G9: Minerales, sal y preñar, Dosis de refuerzo el 19-02-27 | H9: 0
A10: 3C | B10: Hijo 1799 | C10: Macho | D10: 46051 | E10: Ricomax 5ml-Vacuna carbon 1era dosis, curagan en cuerno. | F10: Dr. Zuñiga | G10: Dosis de refuerzo el 19-02-26 | H10: 0
A11: 3C | B11: 1757 | C11: Hembra | D11: 46051 | E11: Ricomax 15cc subcutáneo-Vacuna Reproductiv. Imidocar- Eco: útero sin tono útero en anestro. Abcseso en gluteo, se drenó, impresiona babesia, No ordeñar. | F11: Dr. Zuñiga | G11: Minerales y preñar | H11: 0
A12: 3C | B12: Hijo de 1757 | C12: Macho | D12: 46051 | E12: Ricomax 5ml-Vacuna carbon 1era dosis | F12: Dr. Zuñiga | G12: Dosis de refuerzo el 19-02-26 | H12: 0
A13: 3C | B13: 320-N23 | C13: Hembra | D13: 46051 | E13: Ricomax 15ml | F13: Dr. Zuñiga | G13: Pendiente vacunas | H13: 0
A14: 3C | B14: 348-124 | C14: Hembra | D14: 46051 | E14: Ricomax 15ml | F14: Dr. Zuñiga | G14: Pendiente vacunas | H14: 0
A15: 3C | B15: 330-D23 | C15: Hembra | D15: 46051 | E15: Ricomax 15ml | F15: Dr. Zuñiga | G15: Pendiente vacunas | H15: 0
A16: 3C | B16: 327-D23 | C16: Hembra | D16: 46051 | E16: Ricomax 15ml | F16: Dr. Zuñiga | G16: Pendiente vacunas | H16: 0
A17: 3C | B17: 347-124 | C17: Hembra | D17: 46051 | E17: Ricomax 15ml | F17: Dr. Zuñiga | G17: Pendiente vacunas | H17: 0
A18: 3C | B18: 328-D23 | C18: Hembra | D18: 46051 | E18: Ricomax 15ml | F18: Dr. Zuñiga | G18: Pendiente vacunas | H18: 0
A19: 3C | B19: 350-124 | C19: Hembra | D19: 46051 | E19: Ricomax 15ml | F19: Dr. Zuñiga | G19: Pendiente vacunas | H19: 0
A20: 3C | B20: 345-124 | C20: Hembra | D20: 46051 | E20: Ricomax 15ml | F20: Dr. Zuñiga | G20: Pendiente vacunas | H20: 0
A21: 3C | B21: 1697-0 | C21: Hembra | D21: 46065 | E21: Baño con Amitrax, Ricomax 15 cc SC, AZ5 15CC SC | F21: Francisco | G21: Esquema baño 0-7-14-21 | H21: 0
A22: 3C | B22: Hijo de 1697-0 | C22: hembra | D22: 46065 | E22: Baño con Amitrax, Ricomax 5 cc SC, AZ5 15CC SC | F22: Francisco | G22: Esquema baño 0-7-14-22 | H22: 0
A23: 3C | B23: 504 | C23: Hembra | D23: 46065 | E23: Baño con Amitrax, AZ5 15CC SC | F23: Francisco | G23: Esquema baño 0-7-14-23 | H23: 0
A24: 3C | B24: Hijo de 504 | C24: Hembra | D24: 46065 | E24: Baño con Amitrax | F24: Francisco | G24: Esquema baño 0-7-14-24 | H24: 0
A25: 3C | B25: 1479-0 | C25: Hembra | D25: 46065 | E25: Baño con Amitrax, AZ5 15CC SC | F25: Francisco | G25: Esquema baño 0-7-14-25 | H25: 0
A26: 3C | B26: 1751-0 | C26: Hembra | D26: 46065 | E26: Baño con Amitrax, AZ5 15CC SC | F26: Francisco | G26: Esquema baño 0-7-14-26 | H26: 0
A27: 3C | B27: Hijo de 1751 | C27: Hembra | D27: 46065 | E27: Baño con Amitrax | F27: Francisco | G27: Esquema baño 0-7-14-27 | H27: 0
A28: 3C | B28: 1731-0 | C28: Hembra | D28: 46065 | E28: Baño con Amitrax, AZ5 15CC SC | F28: Francisco | G28: Esquema baño 0-7-14-28 | H28: 0
A29: 3C | B29: Hijo de 1731 | C29: Macho | D29: 46065 | E29: Baño con Amitrax | F29: Francisco | G29: Esquema baño 0-7-14-29 | H29: 0
A30: 3C | B30: 1799 | C30: Hembra | D30: 46065 | E30: Baño con Amitrax, AZ5 15CC SC | F30: Francisco | G30: Esquema baño 0-7-14-30 | H30: 0
A31: 3C | B31: Hijo 1799 | C31: Macho | D31: 46065 | E31: Baño con Amitrax | F31: Francisco | G31: Esquema baño 0-7-14-31 | H31: 0
A32: 3C | B32: 1757 | C32: Hembra | D32: 46065 | E32: Baño con Amitrax, AZ5 15CC SC | F32: Francisco | G32: Esquema baño 0-7-14-32 | H32: 0
A33: 3C | B33: Hijo de 1757 | C33: Macho | D33: 46065 | E33: Baño con Amitrax | F33: Francisco | G33: Esquema baño 0-7-14-33 | H33: 0
A34: 3C | B34: 320-N23 | C34: Hembra | D34: 46065 | E34: Baño con Amitrax | F34: Francisco | G34: Esquema baño 0-7-14-34 | H34: 0
A35: 3C | B35: 348-124 | C35: Hembra | D35: 46065 | E35: Baño con Amitrax | F35: Francisco | G35: Esquema baño 0-7-14-35 | H35: 0
A36: 3C | B36: 330-D23 | C36: Hembra | D36: 46065 | E36: Baño con Amitrax | F36: Francisco | G36: Esquema baño 0-7-14-36 | H36: 0
A37: 3C | B37: 327-D23 | C37: Hembra | D37: 46065 | E37: Baño con Amitrax | F37: Francisco | G37: Esquema baño 0-7-14-37 | H37: 0
A38: 3C | B38: 347-124 | C38: Hembra | D38: 46065 | E38: Baño con Amitrax | F38: Francisco | G38: Esquema baño 0-7-14-38 | H38: 0
A39: 3C | B39: 328-D23 | C39: Hembra | D39: 46065 | E39: Baño con Amitrax | F39: Francisco | G39: Esquema baño 0-7-14-39 | H39: 0
A40: 3C | B40: 350-124 | C40: Hembra | D40: 46065 | E40: Baño con Amitrax | F40: Francisco | G40: Esquema baño 0-7-14-40 | H40: 0
A41: 3C | B41: 345-124 | C41: Hembra | D41: 46065 | E41: Baño con Amitrax | F41: Francisco | G41: Esquema baño 0-7-14-41 | H41: 0
A42: 3C | B42: Shakira | C42: Hembra | D42: 46065 | E42: Baño con Amitrax | F42: Francisco | G42: Esquema baño 0-7-14-42 | H42: 0
A43: 3C | B43: Siete Mujeres | C43: Macho | D43: 46065 | E43: Baño con Amitrax | F43: Francisco | G43: Esquema baño 0-7-14-43 | H43: 0
A44: 3C | B44: Carol | C44: Hembra | D44: 46065 | E44: Baño con Amitrax | F44: Francisco | G44: Esquema baño 0-7-14-44 | H44: 0
... A47: 3C | B47: Dina Luz - 018 | C47: Hembra | D47: 46065 | E47: Baño con Amitrax | F47: Francisco | G47: Esquema baño 0-7-14-47 | H47: 0
A48: Guadalupe | B48: 52 "Nikita" | C48: Hembra | D48: 17/12/2025- enero y febrero 26 | E48: Hematura persistente, multiples manejos, persiste sangrado, descartada causa infecciosa, sin afectacion sistemica. Ceftriofur, vetercilin, Flunixilin, estrozoo. ATB intramamario por una teta con mastitis. Kavitex f1, quercetol, gluconato de calcio, pomada antiflojistica vacol, sulfato de magnesio, vitamina K, domosyn, dexametazona. | F48: Dr. Zuñiga | H48: 0
A49: Guadalupe | B49: 47 "mamá de Copito" | C49: Hembra | D49: 46020 | E49: Palida, delgada decaida, baja produccion, se aplica proxy, flumegan, incremento de concentrado. | F49: Dr. Zuñiga | H49: 0
A50: Guadalupe | B50: 47 "mamá de Copito" | C50: Hembra | D50: 46051 | E50: Presenta dolor abdominal marcado, se le aplica atb y analgesico. | F50: Dr. Zuñiga | H50: 0
A51: Guadalupe | B51: 21 | C51: Hembra | D51: 46064 | E51: palida, decaida, muy delgada, se le aplica Dimoxiproc, tiamina IM, IMICAR | F51: Dr. Zuñiga | H51: 0
A52: Guadalupe | B52: Hijo de 021 "Tomas de Aquino" | C52: Macho | D52: 46066 | E52: Regular estaod general, fiebre, se aplica ampisulbactam-quincalf, fluxilin por fiebre | F52: Dr. Zuñiga | H52: 0
A53: Guadalupe | B53: Victoria | C53: Hembra | D53: 46072 | E53: Baño con amitrax dos dias seguidos, continuar esquema 0-7-14-21 | F53: Manuel Gonzalez | H53: 0
A54: Guadalupe | B54: Paturra | C54: Hembra | D54: 46072 | E54: Baño con amitrax dos dias seguidos, continuar esquema 0-7-14-22 | F54: Manuel Gonzalez | H54: 0
A55: Guadalupe | B55: Reina de Cartagena | C55: Hembra | D55: 46072 | E55: Baño con amitrax dos dias seguidos, continuar esquema 0-7-14-23 | F55: Manuel Gonzalez | H55: 0
A56: Guadalupe | B56: 403-Indira | C56: Hembra | D56: 46072 | E56: Baño con amitrax dos dias seguidos, continuar esquema 0-7-14-24 | F56: Manuel Gonzalez | H56: 0
A57: Guadalupe | B57: Hijo de Indira H de 403 | C57: Macho | D57: 46072 | E57: Baño con amitrax dos dias seguidos, continuar esquema 0-7-14-29, se baña con yodo 5 dias seguidos | F57: Manuel Gonzalez | H57: 0
A58: Guadalupe | B58: 21 | C58: Hembra | D58: 46072 | E58: Baño con amitrax dos dias seguidos, continuar esquema 0-7-14-26 | F58: Manuel Gonzalez | H58: 0
A59: Guadalupe | B59: Hijo de 021 "Tomas de Aquino" | C59: Macho | D59: 46072 | E59: Baño con amitrax dos dias seguidos, continuar esquema 0-7-14-27 | F59: Manuel Gonzalez | H59: 0
A60: Guadalupe | B60: 47 "mamá de Copito" | C60: Hembra | D60: 46072 | E60: Baño con amitrax dos dias seguidos, continuar esquema 0-7-14-28 | F60: Manuel Gonzalez | H60: 0
A61: Guadalupe | B61: Hijo de 047- "Copito" | C61: Macho | D61: 46072 | E61: Baño con amitrax dos dias seguidos, continuar esquema 0-7-14-29, se baña con yodo 5 dias seguidos | F61: Manuel Gonzalez | H61: 0
A62: Guadalupe | B62: H de 073 "BLAS"- Huerfano | C62: Macho | D62: 46072 | E62: Baño con amitrax dos dias seguidos, continuar esquema 0-7-14-30 | F62: Manuel Gonzalez | H62: 0
A63: Guadalupe | B63: 53 | C63: Hembra | D63: 46072 | E63: Baño con amitrax dos dias seguidos, continuar esquema 0-7-14-31 | F63: Manuel Gonzalez | H63: 0
A64: Guadalupe | B64: Hijo de 053 "Lluvia" | C64: Hembra | D64: 46072 | E64: Baño con amitrax dos dias seguidos, continuar esquema 0-7-14-32 | F64: Manuel Gonzalez | H64: 0
A65: Guadalupe | B65: 45 "Azabache" | C65: Hembra | D65: 46072 | E65: Baño con amitrax dos dias seguidos, continuar esquema 0-7-14-33 | F65: Manuel Gonzalez | H65: 0
A66: Guadalupe | B66: Hijo de 045 "Diana" | C66: Hembra | D66: 46072 | E66: Baño con amitrax dos dias seguidos, continuar esquema 0-7-14-34 | F66: Manuel Gonzalez | H66: 0
A67: Guadalupe | B67: 38 | C67: Hembra | D67: 46072 | E67: Baño con amitrax dos dias seguidos, continuar esquema 0-7-14-35 | F67: Manuel Gonzalez | H67: 0
A68: Guadalupe | B68: 186 "Noche" | C68: Hembra | D68: 46072 | E68: Baño con amitrax dos dias seguidos, continuar esquema 0-7-14-36 | F68: Manuel Gonzalez | H68: 0
A69: Guadalupe | B69: Hijo de 186 "Noche" | C69: Macho | D69: 46072 | E69: Baño con amitrax dos dias seguidos, continuar esquema 0-7-14-37 | F69: Manuel Gonzalez | H69: 0
A70: Guadalupe | B70: 52 "Nikita" | C70: Hembra | D70: 46072 | E70: Baño con amitrax dos dias seguidos, continuar esquema 0-7-14-38 | F70: Manuel Gonzalez | H70: 0
A71: Guadalupe | B71: Hijo de 052 "Nikita" | C71: Hembra | D71: 46072 | E71: Baño con amitrax dos dias seguidos, continuar esquema 0-7-14-39 | F71: Manuel Gonzalez | H71: 0
A72: Guadalupe | B72: 78 | C72: Hembra | D72: 46072 | E72: Baño con amitrax dos dias seguidos, continuar esquema 0-7-14-40 | F72: Manuel Gonzalez | H72: 0
A73: Guadalupe | B73: 1317 "Cariñosa" | C73: Hembra | D73: 46072 | E73: Baño con amitrax dos dias seguidos, continuar esquema 0-7-14-41 | F73: Manuel Gonzalez | H73: 0
A74: Guadalupe | B74: Hijo de 1317 "Cariñito" | C74: Hembra | D74: 46072 | E74: Baño con amitrax dos dias seguidos, continuar esquema 0-7-14-42 | F74: Manuel Gonzalez | H74: 0
A75: Guadalupe | B75: 1152 | C75: Hembra | D75: 46072 | E75: Baño con amitrax dos dias seguidos, continuar esquema 0-7-14-43 | F75: Manuel Gonzalez | H75: 0
A76: Guadalupe | B76: 818-3 | C76: Hembra | D76: 46072 | E76: Baño con amitrax dos dias seguidos, continuar esquema 0-7-14-44 | F76: Manuel Gonzalez | H76: 0
A77: Guadalupe | B77: Victoria | C77: Hembra | D77: 46069 | E77: Pendiente cortar la cola, infeccion por hongos. Mastitis se aplica antimastitico intramamario | F77: Manuel Gonzalez | H77: 0
A78: Guadalupe | B78: Victoria | C78: Hembra | D78: 46063 | E78: Eprinomectrina 5cc SC Tabla del cuello | F78: Manuel Gonzalez | G78: Garrapatas post emergencia invernal | H78: 0
A79: Guadalupe | B79: Paturra | C79: Hembra | D79: 46063 | E79: Eprinomectrina 5cc SC Tabla del cuello | F79: Manuel Gonzalez | G79: Garrapatas post emergencia invernal | H79: 0
A80: Guadalupe | B80: Reina de Cartagena | C80: Hembra | D80: 46063 | E80: Eprinomectrina 5cc SC Tabla del cuello | F80: Manuel Gonzalez | G80: Garrapatas post emergencia invernal | H80: 0
A81: Guadalupe | B81: 403-Indira | C81: Hembra | D81: 46063 | E81: Eprinomectrina 5cc SC Tabla del cuello | F81: Manuel Gonzalez | G81: Garrapatas post emergencia invernal | H81: 0
A82: Guadalupe | B82: Hijo de Indira H de 403 | C82: Macho | D82: 46063 | E82: Ivermectina 2cc SC | F82: Manuel Gonzalez | G82: Garrapatas post emergencia invernal | H82: 0
A83: Guadalupe | B83: 21 | C83: Hembra | D83: 46063 | E83: Eprinomectrina 5cc SC Tabla del cuello | F83: Manuel Gonzalez | G83: Garrapatas post emergencia invernal | H83: 0
A84: Guadalupe | B84: Hijo de 021 "Tomas de Aquino" | C84: Macho | D84: 46063 | E84: Ivermectina 2cc SC | F84: Manuel Gonzalez | G84: Garrapatas post emergencia invernal | H84: 0
A85: Guadalupe | B85: 47 "mamá de Copito" | C85: Hembra | D85: 46063 | E85: Eprinomectrina 5cc SC Tabla del cuello | F85: Manuel Gonzalez | G85: Garrapatas post emergencia invernal | H85: 0
A86: Guadalupe | B86: Hijo de 047- "Copito" | C86: Macho | D86: 46063 | E86: Ivermectina 2cc SC | F86: Manuel Gonzalez | G86: Garrapatas post emergencia invernal | H86: 0
A87: Guadalupe | B87: H de 073 "BLAS"- Huerfano | C87: Macho | D87: 46063 | E87: Ivermectina 2cc SC | F87: Manuel Gonzalez | G87: Garrapatas post emergencia invernal | H87: 0
A88: Guadalupe | B88: 53 | C88: Hembra | D88: 46063 | E88: Eprinomectrina 5cc SC Tabla del cuello | F88: Manuel Gonzalez | G88: Garrapatas post emergencia invernal | H88: 0
A89: Guadalupe | B89: Hijo de 053 "Lluvia" | C89: Hembra | D89: 46063 | E89: Ivermectina 2cc SC | F89: Manuel Gonzalez | G89: Garrapatas post emergencia invernal | H89: 0
A90: Guadalupe | B90: 45 "Azabache" | C90: Hembra | D90: 46063 | E90: Eprinomectrina 5cc SC Tabla del cuello | F90: Manuel Gonzalez | G90: Garrapatas post emergencia invernal | H90: 0
A91: Guadalupe | B91: Hijo de 045 "Diana" | C91: Hembra | D91: 46063 | E91: Ivermectina 2cc SC | F91: Manuel Gonzalez | G91: Garrapatas post emergencia invernal | H91: 0
A92: Guadalupe | B92: 38 | C92: Hembra | D92: 46063 | E92: Eprinomectrina 5cc SC Tabla del cuello | F92: Manuel Gonzalez | G92: Garrapatas post emergencia invernal | H92: 0
A93: Guadalupe | B93: 186 "Noche" | C93: Hembra | D93: 46063 | E93: Eprinomectrina 5cc SC Tabla del cuello | F93: Manuel Gonzalez | G93: Garrapatas post emergencia invernal | H93: 0
A94: Guadalupe | B94: Hijo de 186 "Noche" | C94: Macho | D94: 46063 | E94: Ivermectina 2cc SC | F94: Manuel Gonzalez | G94: Garrapatas post emergencia invernal | H94: 0
A95: Guadalupe | B95: 52 "Nikita" | C95: Hembra | D95: 46063 | E95: Eprinomectrina 5cc SC Tabla del cuello | F95: Manuel Gonzalez | G95: Garrapatas post emergencia invernal | H95: 0
A96: Guadalupe | B96: Hijo de 052 "Nikita" | C96: Hembra | D96: 46063 | E96: Ivermectina 2cc SC | F96: Manuel Gonzalez | G96: Garrapatas post emergencia invernal | H96: 0
A97: Guadalupe | B97: 78 | C97: Hembra | D97: 46063 | E97: Eprinomectrina 5cc SC Tabla del cuello | F97: Manuel Gonzalez | G97: Garrapatas post emergencia invernal | H97: 0
A98: Guadalupe | B98: 1317 "Cariñosa" | C98: Hembra | D98: 46063 | E98: Eprinomectrina 5cc SC Tabla del cuello | F98: Manuel Gonzalez | G98: Garrapatas post emergencia invernal | H98: 0
A99: Guadalupe | B99: Hijo de 1317 "Cariñito" | C99: Hembra | D99: 46063 | E99: Ivermectina 2cc SC | F99: Manuel Gonzalez | G99: Garrapatas post emergencia invernal | H99: 0
A100: Guadalupe | B100: 1152 | C100: Hembra | D100: 46063 | E100: Eprinomectrina 5cc SC Tabla del cuello | F100: Manuel Gonzalez | G100: Garrapatas post emergencia invernal | H100: 0
A101: Guadalupe | B101: 818-3 | C101: Hembra | D101: 46063 | E101: Eprinomectrina 5cc SC Tabla del cuello | F101: Manuel Gonzalez | G101: Garrapatas post emergencia invernal | H101: 0

Sheet Compra_Leche
A1: Periodo | B1: Litros | C1: Valor/Litro (COP) | D1: Total (COP)
A2: 05-01-26 al 11-01-26 | B2: 704 | C2: 2000 | D2: 1408000
A3: 12-01-26 al 18-01-26 | B3: 847 | C3: 2000 | D3: 1694000
A4: 19-01-26 al 25-01-26 | B4: 832 | C4: 2000 | D4: 1664000
A5: 26-01-26 al 01-02-26 | B5: 937 | C5: 2000 | D5: 1874000
A6: 02-02-26 al 08-02-26 | B6: 867 | C6: 2000 | D6: 1734000

Sheet Transporte_Leche
A1: Periodo | B1: Valor Transporte (COP) | C1: Cantidad | D1: Total (COP)
A2: 05-01-26 al 11-01-26 | B2: 8000 | C2: 7 | D2: 56000
A3: 12-01-26 al 18-01-26 | B3: 12000 | C3: 7 | D3: 84000
A4: 19-01-26 al 25-01-26 | B4: 12000 | C4: 7 | D4: 84000
A5: 26-01-26 al 01-02-26 | B5: 12000 | C5: 7 | D5: 84000
A6: 02-02-26 al 08-02-26 | B6: 12000 | C6: 7 | D6: 84000
A7: 09-02-26 al 15-02-26 | B7: 12000 | C7: 7 | D7: 84000

Sheet Transporte_Queso
A1: Periodo | B1: Valor Transporte (COP) | C1: Cantidad | D1: Total (COP) | E1: Notas
A2: 19-01-26 al 25-01-26
A3: 26-01-26 al 01-02-26
A4: 02-02-26 al 08-02-26
A5: 09-02-26 al 15-02-26

Sheet Venta_Queso
A1: Fecha | B1: Cliente | C1: Libras | D1: Precio (COP) | E1: Total (COP) | F1: Fondo
A2: 46041 | B2: Nicolas Casab | C2: 61.8 | D2: 9000 | E2: 556200 | F2: Nequi
A3: 46043 | B3: Nicolas Casab | C3: 46.4 | D3: 9000 | E3: 417600 | F3: Nequi
A4: 46043 | B4: Tienda Vereda Malagana | C4: 10.5 | D4: 10000 | E4: 105000 | F4: Nequi
A5: 46044 | B5: Diana | C5: 18 | D5: 9500 | E5: 171000 | F5: Nequi
A6: 46044 | B6: Irma | C6: 3 | D6: 11000 | E6: 33000 | F6: Nequi
A7: 46044 | B7: Viviana Clinica | C7: 5.5 | D7: 11000 | E7: 60500 | F7: Nequi
A8: 46044 | B8: Nicolas Casab | C8: 32.8 | D8: 9000 | E8: 295200 | F8: Nequi
A9: 46045 | B9: Tienda Vereda Malagana | C9: 10 | D9: 10000 | E9: 100000 | F9: Nequi
A10: 46047 | B10: Nicolas Casab | C10: 83.4 | D10: 9000 | E10: 750600 | F10: Nequi
A11: 46048 | B11: Tienda Vereda Malagana | C11: 11.2 | D11: 10000 | E11: 112000 | F11: Nequi
A12: 46050 | B12: Nicolas Casab | C12: 92.4 | D12: 9000 | E12: 831600 | F12: Nequi
A13: 46053 | B13: Nicolas Casab | C13: 73.8 | D13: 9000 | E13: 664200 | F13: Nequi
... A28: 46064 | B28: Lobo | C28: 19.7 | D28: 10000 | E28: 197000 | F28: Nequi
A29: 46066 | B29: Nicolas Casab | C29: 16 | D29: 10000 | E29: 160000
A30: 46066 | B30: Nicolas Casab | C30: 70.3 | D30: 10000 | E30: 703000
A31: 46067 | B31: Noelia | C31: 24.4 | D31: 10000 | E31: 244000
A32: 46068 | B32: Nicolas Casab
A33: 46069 | B33: Nicolas Casab

Sheet Gastos_Fijos
A1: Concepto | B1: Valor Mensual (COP) | C1: Notas
A2: Nomina Colaboradores | B2: 6500000
A3: Seg Social | B3: 2000000
A4: Aseo OPS | B4: 320000
A5: Nomina Contador | B5: 1500000
A6: Revisor Fiscal | B6: 2000000
A7: Servicios Publicos | B7: 2000000
A8: TV-Internet | B8: 150000
A9: Veterinario | B9: 300000
A10: Medicamentos e insumos animales/mes | B10: 1500000
A11: Alimentos e insumos de aseo/EPP | B11: 1500000
A12: Herbicidas/plagicidas/suelo | B12: 500000
A13: Insumos Queso | B13: 250000
... A16: Suplementación Bovinos | B16: 1000000
A17: (Queso) Compra leche | B17: 3000000 | C17: Sale de la produccion del queso
A18: (Queso) Mensajero busca leche | B18: 240000
A19: (Queso) Transporte queso Nicolás | B19: 250000

Sheet Dashboard_Resumen
A1: Indicador | B1: Valor (COP)
A2: Total compra leche | B2: 8374000
A3: Total transporte leche | B3: 476000
A4: Total ventas queso | B4: 9746900
A5: Total medicamentos | B5: 0

Sheet Produccion_Diaria
A1: Fecha | B1: Arete | C1: Finca | D1: Nombre | E1: Litros Mañana | F1: Litros Tarde | G1: Total Litros
B2: 6 | C2: Guadalupe | D2: Victoria | E2: 4
B3: 10 | C3: Guadalupe | D3: Paturra
B4: 16 | C4: Guadalupe | D4: Reina de Cartagena
B5: 403 | C5: Guadalupe | D5: 403-Indira
B6: 11 | C6: Guadalupe | D6: Hijo de Indira H de 403
B7: 21 | C7: Guadalupe | D7: 21
C8: Guadalupe | D8: Hijo de 021 "Tomas de Aquino"
B9: 47 | C9: Guadalupe | D9: 47 "mamá de Copito"
C10: Guadalupe | D10: Hijo de 047- "Copito"
C11: Guadalupe | D11: H de 073 "BLAS"- Huerfano
B12: 53 | C12: Guadalupe | D12: 53
C13: Guadalupe | D13: Hijo de 053 "Lluvia"
C14: Guadalupe | D14: 45 "Azabache"
B15: 45 | C15: Guadalupe | D15: Hijo de 045 "Diana"
B16: 38 | C16: Guadalupe | D16: 38
B17: 186 | C17: Guadalupe | D17: 186 "Noche"
C18: Guadalupe | D18: Hijo de 186 "Noche"
B19: 52 | C19: Guadalupe | D19: 52 "Nikita"
C20: Guadalupe | D20: Hijo de 052 "Nikita"
B21: 78 | C21: Guadalupe | D21: 78
B22: 1317 | C22: Guadalupe | D22: 1317 "Cariñosa"
C23: Guadalupe | D23: Hijo de 1317 "Cariñito"
B24: 1152 | C24: Guadalupe | D24: 1152
B25: 818 | C25: Guadalupe | D25: 818-3
B26: 4 | C26: 3C | D26: Shakira
B27: 3 | C27: 3C | D27: Siete Mujeres
B28: 22 | C28: 3C | D28: Carol
B29: 14 | C29: 3C | D29: Paturra Hija
B30: 1 | C30: 3C | D30: Ramsés
B31: 320 | C31: 3C | D31: 320-N23
B32: 348 | C32: 3C | D32: 348-124
B33: 330 | C33: 3C | D33: 330-D23
B34: 327 | C34: 3C | D34: 327-D23
B35: 347 | C35: 3C | D35: 347-124
B36: 328 | C36: 3C | D36: 328-D23
... B39: 18 | C39: 3C | D39: Dina Luz - 018
B40: 1751 | C40: 3C | D40: 1751
B41: 42 | C41: 3C | D41: Hijo de 1751
B42: 1557 | C42: 3C | D42: 1757-0
B43: 29 | C43: 3C | D43: Hijo de 1757-0
B44: 1731 | C44: 3C | D44: 1731-0
B45: 31 | C45: 3C | D45: Hijo de 1731-0
B46: 1697 | C46: 3C | D46: 1697-0
B47: 33 | C47: 3C | D47: Hijo de 1697-0
B48: 1799 | C48: 3C | D48: 1799-0
B49: 35 | C49: 3C | D49: Hijo de 1799-0
B50: 504 | C50: 3C | D50: 504-220
B51: 44 | C51: 3C | D51: Hijo de 504-220
B52: 1479 | C52: 3C | D52: 1479-0
B53: 46 | C53: 3C | D53: Hijo de 1479-0
B54: 116-9 | C54: 3C | D54: 116-9
B55: 1726 | C55: 3C | D55: 1726
B56: 1810 | C56: 3C | D56: 1810-0
B57: 127 | C57: 3C | D57: 127
B58: 49 | C58: 3C | D58: 49
B59: 57 | C59: 3C | D59: 57
B60: 294 | C60: 3C | D60: 294-123
B61: 310 | C61: 3C | D61: 310-923

Sheet Vacas_Lactancia
A1: FINCA | B1: Nombre/Arete | C1: Arete | D1: Raza | E1: Fecha Nacimiento
A2: Guadalupe | B2: Victoria | C2: 6 | D2: F1 Simbrah | E2: Desconocida
A3: Guadalupe | B3: Paturra | C3: 10 | D3: Brahman PATURRA | E3: Desconocida
A4: Guadalupe | B4: Reina de Cartagena | C4: 16 | D4: GYR | E4: 43313
A5: Guadalupe | B5: 403-Indira | C5: 403 | D5: Girolanda F1
A6: Guadalupe | B6: 21 | C6: 21 | D6: Girolanda F1
A7: Guadalupe | B7: 47 "mamá de Copito" | C7: 47 | D7: Girolanda F1
A8: Guadalupe | B8: 53 | C8: 53 | D8: Girolanda F1
A9: Guadalupe | B9: Hijo de 053 "Lluvia" | D9: Girolanda F2 | E9: 46057
A10: Guadalupe | B10: 45 "Azabache" | D10: Girolanda F1
A11: Guadalupe | B11: Hijo de 045 "Diana" | C11: 45 | D11: Girolanda F2 | E11: 46036
A12: Guadalupe | B12: 38 | C12: 38 | D12: Girolanda F1
A13: Guadalupe | B13: 186 "Noche" | C13: 186 | D13: Girolanda F1
A14: Guadalupe | B14: 52 "Nikita" | C14: 52 | D14: Girolanda F1
A15: Guadalupe | B15: Hijo de 052 "Nikita" | D15: Girolanda F2 | E15: 45998
A16: Guadalupe | B16: 78 | C16: 78 | D16: Girolanda F1
A17: Guadalupe | B17: 1317 "Cariñosa" | C17: 1317 | D17: Girolanda F1
A18: Guadalupe | B18: Hijo de 1317 "Cariñito" | D18: Girolanda F2 | E18: 46031
A19: Guadalupe | B19: 1152 | C19: 1152 | D19: Girolanda F1
A20: Guadalupe | B20: 818-3 | C20: 818 | D20: Girolanda F1 | E20: 45174
A21: 3C | B21: Shakira | C21: 4 | D21: Parda Suizo x Cebu PATURRA | E21: Desconocida
A22: 3C | B22: Carol | C22: 22 | D22: No especifico | E22: 45905
A23: 3C | B23: Paturra Hija | C23: 14 | D23: Brahman Rojo PATURRA | E23: Desconocida
A24: 3C | B24: 320-N23 | C24: 320 | D24: Girolanda
A25: 3C | B25: 348-124 | C25: 348 | D25: Girolanda Plus | E25: 45307
A26: 3C | B26: 330-D23 | C26: 330 | D26: Girolanda Plus | E26: 45270
A27: 3C | B27: 327-D23 | C27: 327 | D27: Girolanda Plus | E27: 45270
A28: 3C | B28: 347-124 | C28: 347 | D28: Girolanda Plus | E28: 45304
A29: 3C | B29: 328-D23 | C29: 328 | D29: Girolanda Plus | E29: 45270
A30: 3C | B30: 350-124 | C30: 350 | D30: Girolanda Plus | E30: 45309
A31: 3C | B31: 345-124 | C31: 345 | D31: Girolanda Plus | E31: 45304
A32: 3C | B32: Dina Luz - 018 | C32: 18 | D32: Red Shindi | E32: 45685
A33: 3C | B33: 1751 | C33: 1751 | D33: Simbrah | E33: 44166
A34: 3C | B34: Hijo de 1751 | C34: 42 | D34: Simbrah | E34: 45916
A35: 3C | B35: 1757-0 | C35: 1557 | D35: Simbrah | E35: 44166
A36: 3C | B36: 1731-0 | C36: 1731 | D36: Simbrah
A37: 3C | B37: 1697-0 | C37: 1697 | D37: Simbrah
A38: 3C | B38: Hijo de 1697-0 | C38: 33 | D38: Simbrah | E38: 45939
A39: 3C | B39: 1799-0 | C39: 1799 | D39: Simbrah | E39: 44169
A40: 3C | B40: 504-220 | C40: 504 | D40: Simbrah | E40: 43881
A41: 3C | B41: Hijo de 504-220 | C41: 44 | D41: Simbrah | E41: 45983
A42: 3C | B42: 1479-0 | C42: 1479 | D42: Simbrah | E42: 44127
A43: 3C | B43: Hijo de 1479-0 | C43: 46 | D43: Simbrah
A44: 3C | B44: 116-9 | C44: 116-9 | D44: Simbrah | E44: 43829
A45: 3C | B45: 1726 | C45: 1726 | D45: Simbrah
A46: 3C | B46: 1810-0 | C46: 1810 | D46: Simbrah | E46: 44175
A47: 3C | B47: 127 | C47: 127 | D47: Girolanda F1
A48: 3C | B48: 49 | C48: 49 | D48: Girolanda F1
A49: 3C | B49: 57 | C49: 57 | D49: Girolanda F1
A50: 3C | B50: 294-123 | C50: 294 | D50: Girolanda Plus | E50: 45125
A51: 3C | B51: 310-923 | C51: 310 | D51: Girolanda Plus | E51: 45184

Sheet Punto_Equilibrio
A1: Concepto | B1: Valor
A2: Precio litro (ingrese)
A3: Litros producidos
A4: Ingreso por leche
A5: Gastos fijos
A6: Resultado operativo

Sheet Control_Reproductivo
A1: Arete | B1: Nombre | C1: Fecha Último Parto | D1: Fecha Último Celo | E1: Fecha Inseminación | F1: Diagnóstico Preñez (SI/NO) | G1: Fecha Probable Parto | H1: Días Abiertos | I1: Alerta

Sheet Indicadores_Repro
A1: Indicador | B1: Valor
A2: Total Vacas en Control
A3: Vacas Preñadas
A4: Promedio Días Abiertos
A5: Vacas con Alerta

Sheet Ranking_Vacas
A1: Arete | B1: Nombre | C1: Litros Mes | D1: Ingreso Mes (COP)
A2: 6 | B2: Victoria | C2: =SUMIF(Produccion_Diaria!B:B,A2,Produccion_Diaria!G:G) -> 0 | D2: =C2*Punto_Equilibrio!B1 -> #VALUE!
A3: 10 | B3: Paturra | C3: =SUMIF(Produccion_Diaria!B:B,A3,Produccion_Diaria!G:G) -> 0 | D3: =C3*Punto_Equilibrio!B1 -> #VALUE!
A4: 16 | B4: Reina de Cartagena | C4: =SUMIF(Produccion_Diaria!B:B,A4,Produccion_Diaria!G:G) -> 0 | D4: =C4*Punto_Equilibrio!B1 -> #VALUE!
A5: 403 | B5: 403-Indira | C5: =SUMIF(Produccion_Diaria!B:B,A5,Produccion_Diaria!G:G) -> 0 | D5: =C5*Punto_Equilibrio!B1 -> #VALUE!
A6: 21 | B6: 21 | C6: =SUMIF(Produccion_Diaria!B:B,A6,Produccion_Diaria!G:G) -> 0 | D6: =C6*Punto_Equilibrio!B1 -> #VALUE!
A7: 47 | B7: 47 "mamá de Copito" | C7: =SUMIF(Produccion_Diaria!B:B,A7,Produccion_Diaria!G:G) -> 0 | D7: =C7*Punto_Equilibrio!B1 -> #VALUE!
A8: 53 | B8: 53 | C8: =SUMIF(Produccion_Diaria!B:B,A8,Produccion_Diaria!G:G) -> 0 | D8: =C8*Punto_Equilibrio!B1 -> #VALUE!
B9: Hijo de 053 "Lluvia" | C9: =SUMIF(Produccion_Diaria!B:B,A9,Produccion_Diaria!G:G) -> 0 | D9: =C9*Punto_Equilibrio!B1 -> #VALUE!
B10: 45 "Azabache" | C10: =SUMIF(Produccion_Diaria!B:B,A10,Produccion_Diaria!G:G) -> 0 | D10: =C10*Punto_Equilibrio!B1 -> #VALUE!
A11: 45 | B11: Hijo de 045 "Diana" | C11: =SUMIF(Produccion_Diaria!B:B,A11,Produccion_Diaria!G:G) -> 0 | D11: =C11*Punto_Equilibrio!B1 -> #VALUE!
A12: 38 | B12: 38 | C12: =SUMIF(Produccion_Diaria!B:B,A12,Produccion_Diaria!G:G) -> 0 | D12: =C12*Punto_Equilibrio!B1 -> #VALUE!
A13: 186 | B13: 186 "Noche" | C13: =SUMIF(Produccion_Diaria!B:B,A13,Produccion_Diaria!G:G) -> 0 | D13: =C13*Punto_Equilibrio!B1 -> #VALUE!
A14: 52 | B14: 52 "Nikita" | C14: =SUMIF(Produccion_Diaria!B:B,A14,Produccion_Diaria!G:G) -> 0 | D14: =C14*Punto_Equilibrio!B1 -> #VALUE!
B15: Hijo de 052 "Nikita" | C15: =SUMIF(Produccion_Diaria!B:B,A15,Produccion_Diaria!G:G) -> 0 | D15: =C15*Punto_Equilibrio!B1 -> #VALUE!
A16: 78 | B16: 78 | C16: =SUMIF(Produccion_Diaria!B:B,A16,Produccion_Diaria!G:G) -> 0 | D16: =C16*Punto_Equilibrio!B1 -> #VALUE!
A17: 1317 | B17: 1317 "Cariñosa" | C17: =SUMIF(Produccion_Diaria!B:B,A17,Produccion_Diaria!G:G) -> 0 | D17: =C17*Punto_Equilibrio!B1 -> #VALUE!
B18: Hijo de 1317 "Cariñito" | C18: =SUMIF(Produccion_Diaria!B:B,A18,Produccion_Diaria!G:G) -> 0 | D18: =C18*Punto_Equilibrio!B1 -> #VALUE!
A19: 1152 | B19: 1152 | C19: =SUMIF(Produccion_Diaria!B:B,A19,Produccion_Diaria!G:G) -> 0 | D19: =C19*Punto_Equilibrio!B1 -> #VALUE!
A20: 818 | B20: 818-3 | C20: =SUMIF(Produccion_Diaria!B:B,A20,Produccion_Diaria!G:G) -> 0 | D20: =C20*Punto_Equilibrio!B1 -> #VALUE!
A21: 4 | B21: Shakira | C21: =SUMIF(Produccion_Diaria!B:B,A21,Produccion_Diaria!G:G) -> 0 | D21: =C21*Punto_Equilibrio!B1 -> #VALUE!
A22: 22 | B22: Carol | C22: =SUMIF(Produccion_Diaria!B:B,A22,Produccion_Diaria!G:G) -> 0 | D22: =C22*Punto_Equilibrio!B1 -> #VALUE!
A23: 14 | B23: Paturra Hija | C23: =SUMIF(Produccion_Diaria!B:B,A23,Produccion_Diaria!G:G) -> 0 | D23: =C23*Punto_Equilibrio!B1 -> #VALUE!
A24: 320 | B24: 320-N23 | C24: =SUMIF(Produccion_Diaria!B:B,A24,Produccion_Diaria!G:G) -> 0 | D24: =C24*Punto_Equilibrio!B1 -> #VALUE!
A25: 348 | B25: 348-124 | C25: =SUMIF(Produccion_Diaria!B:B,A25,Produccion_Diaria!G:G) -> 0 | D25: =C25*Punto_Equilibrio!B1 -> #VALUE!
A26: 330 | B26: 330-D23 | C26: =SUMIF(Produccion_Diaria!B:B,A26,Produccion_Diaria!G:G) -> 0 | D26: =C26*Punto_Equilibrio!B1 -> #VALUE!
A27: 327 | B27: 327-D23 | C27: =SUMIF(Produccion_Diaria!B:B,A27,Produccion_Diaria!G:G) -> 0 | D27: =C27*Punto_Equilibrio!B1 -> #VALUE!
A28: 347 | B28: 347-124 | C28: =SUMIF(Produccion_Diaria!B:B,A28,Produccion_Diaria!G:G) -> 0 | D28: =C28*Punto_Equilibrio!B1 -> #VALUE!
A29: 328 | B29: 328-D23 | C29: =SUMIF(Produccion_Diaria!B:B,A29,Produccion_Diaria!G:G) -> 0 | D29: =C29*Punto_Equilibrio!B1 -> #VALUE!
A30: 350 | B30: 350-124 | C30: =SUMIF(Produccion_Diaria!B:B,A30,Produccion_Diaria!G:G) -> 0 | D30: =C30*Punto_Equilibrio!B1 -> #VALUE!
A31: 345 | B31: 345-124 | C31: =SUMIF(Produccion_Diaria!B:B,A31,Produccion_Diaria!G:G) -> 0 | D31: =C31*Punto_Equilibrio!B1 -> #VALUE!
A32: 18 | B32: Dina Luz - 018 | C32: =SUMIF(Produccion_Diaria!B:B,A32,Produccion_Diaria!G:G) -> 0 | D32: =C32*Punto_Equilibrio!B1 -> #VALUE!
A33: 1751 | B33: 1751 | C33: =SUMIF(Produccion_Diaria!B:B,A33,Produccion_Diaria!G:G) -> 0 | D33: =C33*Punto_Equilibrio!B1 -> #VALUE!
A34: 42 | B34: Hijo de 1751 | C34: =SUMIF(Produccion_Diaria!B:B,A34,Produccion_Diaria!G:G) -> 0 | D34: =C34*Punto_Equilibrio!B1 -> #VALUE!
A35: 1557 | B35: 1757-0 | C35: =SUMIF(Produccion_Diaria!B:B,A35,Produccion_Diaria!G:G) -> 0 | D35: =C35*Punto_Equilibrio!B1 -> #VALUE!
A36: 1731 | B36: 1731-0 | C36: =SUMIF(Produccion_Diaria!B:B,A36,Produccion_Diaria!G:G) -> 0 | D36: =C36*Punto_Equilibrio!B1 -> #VALUE!
A37: 1697 | B37: 1697-0 | C37: =SUMIF(Produccion_Diaria!B:B,A37,Produccion_Diaria!G:G) -> 0 | D37: =C37*Punto_Equilibrio!B1 -> #VALUE!
A38: 33 | B38: Hijo de 1697-0 | C38: =SUMIF(Produccion_Diaria!B:B,A38,Produccion_Diaria!G:G) -> 0 | D38: =C38*Punto_Equilibrio!B1 -> #VALUE!
A39: 1799 | B39: 1799-0 | C39: =SUMIF(Produccion_Diaria!B:B,A39,Produccion_Diaria!G:G) -> 0 | D39: =C39*Punto_Equilibrio!B1 -> #VALUE!
A40: 504 | B40: 504-220 | C40: =SUMIF(Produccion_Diaria!B:B,A40,Produccion_Diaria!G:G) -> 0 | D40: =C40*Punto_Equilibrio!B1 -> #VALUE!
A41: 44 | B41: Hijo de 504-220 | C41: =SUMIF(Produccion_Diaria!B:B,A41,Produccion_Diaria!G:G) -> 0 | D41: =C41*Punto_Equilibrio!B1 -> #VALUE!
A42: 1479 | B42: 1479-0 | C42: =SUMIF(Produccion_Diaria!B:B,A42,Produccion_Diaria!G:G) -> 0 | D42: =C42*Punto_Equilibrio!B1 -> #VALUE!
A43: 46 | B43: Hijo de 1479-0 | C43: =SUMIF(Produccion_Diaria!B:B,A43,Produccion_Diaria!G:G) -> 0 | D43: =C43*Punto_Equilibrio!B1 -> #VALUE!
A44: 116-9 | B44: 116-9 | C44: =SUMIF(Produccion_Diaria!B:B,A44,Produccion_Diaria!G:G) -> 0 | D44: =C44*Punto_Equilibrio!B1 -> #VALUE!
A45: 1726 | B45: 1726 | C45: =SUMIF(Produccion_Diaria!B:B,A45,Produccion_Diaria!G:G) -> 0 | D45: =C45*Punto_Equilibrio!B1 -> #VALUE!
A46: 1810 | B46: 1810-0 | C46: =SUMIF(Produccion_Diaria!B:B,A46,Produccion_Diaria!G:G) -> 0 | D46: =C46*Punto_Equilibrio!B1 -> #VALUE!
A47: 127 | B47: 127 | C47: =SUMIF(Produccion_Diaria!B:B,A47,Produccion_Diaria!G:G) -> 0 | D47: =C47*Punto_Equilibrio!B1 -> #VALUE!
A48: 49 | B48: 49 | C48: =SUMIF(Produccion_Diaria!B:B,A48,Produccion_Diaria!G:G) -> 0 | D48: =C48*Punto_Equilibrio!B1 -> #VALUE!
A49: 57 | B49: 57 | C49: =SUMIF(Produccion_Diaria!B:B,A49,Produccion_Diaria!G:G) -> 0 | D49: =C49*Punto_Equilibrio!B1 -> #VALUE!
A50: 294 | B50: 294-123 | C50: =SUMIF(Produccion_Diaria!B:B,A50,Produccion_Diaria!G:G) -> 0 | D50: =C50*Punto_Equilibrio!B1 -> #VALUE!
A51: 310 | B51: 310-923 | C51: =SUMIF(Produccion_Diaria!B:B,A51,Produccion_Diaria!G:G) -> 0 | D51: =C51*Punto_Equilibrio!B1 -> #VALUE!

Sheet Utilidad_Mensual
A1: Concepto | B1: Valor
A2: Ventas Queso | B2: =SUM(Venta_Queso!E:E) -> 9746900
A3: Compra Leche | B3: =SUM(Compra_Leche!D:D) -> 8374000
A4: Transporte Leche | B4: =SUM(Transporte_Leche!D:D) -> 476000
A5: Medicamentos | B5: =SUM(Medicamentos!H:H) -> 0
A6: Gastos Fijos | B6: =SUM(Gastos_Fijos!B:B) -> 30404000
A7: UTILIDAD NETA | B7: =B2-B3-B4-B5-B6 -> -29507100

Sheet Proyeccion_Anual
A1: Concepto | B1: Valor
A2: Utilidad anual proyectada | B2: =Utilidad_Mensual!B7*12 -> -354085200
A3: Litros anuales proyectados | B3: =SUM(Produccion_Diaria!G:G)*12 -> 0

Sheet Panel_Alertas
A1: ALERTAS DE LA FINCA
A3: Vacas con problemas reproductivos | B3: =COUNTIF(Control_Reproductivo!I:I,"REVISAR") -> 0
A4: Registros de baja producción (<4 L) | B4: =COUNTIF(Produccion_Diaria!G:G,"<4") -> 0
A5: Resultado financiero | B5: =IF(Utilidad_Mensual!B7<0,"PERDIDA","UTILIDAD") -> PERDIDA
